clothesline/__init__.py
clothesline/interval_peg.py
clothesline/real_domain_metric.py
clothesline/real_interval.py
clothesline/real_interval_set.py
clothesline/algebra/__init__.py
clothesline/algebra/interval_operations.py
clothesline/algebra/symbols.py
clothesline/base/__init__.py
clothesline/base/base_domain_metric.py
clothesline/base/base_interval.py
clothesline/base/base_interval_set.py
clothesline/enriched/__init__.py
clothesline/enriched/datetime_interval_set.py
clothesline/enriched/string_interval_set.py
clothesline/exceptions/__init__.py
clothesline/generic/__init__.py
clothesline/generic/interval_generic_builder.py
clothesline/generic/interval_generic_utils.py
clothesline/generic/interval_set_generic_utils.py
clothesline-0.1.1.dist-info/LICENSE.txt
clothesline-0.1.1.dist-info/METADATA
clothesline-0.1.1.dist-info/WHEEL
clothesline-0.1.1.dist-info/top_level.txt
clothesline-0.1.1.dist-info/RECORD
