Metadata-Version: 2.1
Name: clothesline
Version: 0.1.1
Summary: An algebra for intervals over a range of continuous values
Home-page: https://github.com/hemidactylus/clothesline
Author: Stefano Lottini
Author-email: sl_@fastmail.com
License: LICENSE.txt
Keywords: sets,intervals,algebra
Platform: UNKNOWN
Classifier: Development Status :: 4 - Beta
Classifier: Intended Audience :: Developers
Classifier: License :: OSI Approved :: Apache Software License
Classifier: Programming Language :: Python :: 3
Classifier: Programming Language :: Python :: 3.7
Classifier: Programming Language :: Python :: 3.8
Classifier: Programming Language :: Python :: 3.9
Classifier: Programming Language :: Python :: 3.10
Classifier: Programming Language :: Python :: 3.11
Classifier: Programming Language :: Python :: 3 :: Only
Requires-Python: >=3.4.*
License-File: LICENSE.txt
